{
  "slug": "2026-05-22-robbin-capta-us-108-mi-ia-e-credito-b2b-via-pix",
  "titulo": "Robbin capta US$ 108 mi: IA e",
  "meta_titulo": "Robbin capta US$ 108 mi: IA e crédito B2B via Pix — SAFIE IA for Business",
  "meta_description": "Robbin levanta US$ 108 milhões para crédito B2B com Pix. Veja o que isso significa juridicamente para fintechs e startups de IA no Brasil.",
  "canonical_url": "https://ia.safie.blog.br/artigos/2026-05-22-robbin-capta-us-108-mi-ia-e-credito-b2b-via-pix.html",
  "data_iso": "2026-05-22T11:01:45Z",
  "data_formatada": "22 de maio de 2026",
  "ano": "2026",
  "tempo_leitura": 4,
  "tema_nome": "Investimento em IA e deep tech",
  "tema_slug": "investimento-ia",
  "resumo_executivo": "A Robbin captou US$ 108 milhões para expandir sua infraestrutura de crédito B2B baseada em Pix, sinalizando maturidade do mercado de fintechs com IA no Brasil. Do ponto de vista jurídico, a operação envolve regulação do Banco Central, compliance de crédito e estruturação contábil de instrumentos híbridos. Para founders e investidores em deep tech, o caso ilustra como infraestrutura de pagamentos instantâneos pode ser o ativo central de teses de investimento.",
  "conteudo": "<p>Em maio de 2026, a Robbin anunciou uma captação de US$ 108 milhões destinada a ampliar sua plataforma de crédito B2B construída sobre a infraestrutura do Pix. A informação foi divulgada pelo Startupi e representa um dos maiores aportes do ano para fintechs brasileiras com componente tecnológico intensivo.</p>\n<p>O modelo da Robbin não é trivial: usa dados de fluxo de pagamentos via Pix para avaliar risco de crédito de empresas, substituindo parte do processo tradicional de análise bancária. Isso coloca a startup na interseção entre infraestrutura de pagamentos, inteligência artificial e mercado de crédito corporativo.</p>\n<p>Para o ecossistema brasileiro de IA e deep tech, o aporte é relevante não apenas pelo volume, mas pelo que sinaliza: investidores institucionais estão dispostos a alocar capital significativo em modelos que combinam dados transacionais em tempo real com decisão automatizada de crédito.</p>\n\n<h2>Contexto jurídico e regulatório</h2>\n<h2>Regulação de crédito B2B com infraestrutura de Pix</h2>\n<p>A operação da Robbin transita por ao menos três camadas regulatórias no Brasil. A primeira é a Resolução BCB nº 1 de 2020, que instituiu o Pix, e suas normas complementares, que definem quem pode acessar os dados transacionais do sistema e sob quais condições. Usar o Pix como fonte de dados para concessão de crédito exige que a empresa esteja enquadrada como Instituição de Pagamento (IP) ou opere em parceria com uma IF autorizada pelo Banco Central.</p>\n<p>A segunda camada é a Lei nº 4.595/1964 combinada com a Resolução CMN nº 4.656/2018, que criou as Fintechs de Crédito (SEP e SCD). A Sociedade de Crédito Direto (SCD) permite que fintechs concedam crédito com recursos próprios, sem captar depósitos do público. A Sociedade de Empréstimo entre Pessoas (SEP) viabiliza o modelo de marketplace de crédito. A Robbin precisa estar enquadrada em uma dessas categorias ou operar via parceria estruturada com banco autorizado.</p>\n<p>A terceira camada é a Lei Geral de Proteção de Dados (Lei nº 13.709/2018, LGPD). Usar dados de pagamento para inferir capacidade de crédito configura tratamento de dados pessoais sensíveis do ponto de vista econômico-financeiro. Isso exige base legal adequada (consentimento ou legítimo interesse documentado), política de retenção e mecanismos de auditoria de algoritmos de decisão.</p>\n<p>Há ainda um ponto de atenção específico para startups que usam IA na análise de crédito: o Projeto de Lei 2.338/2023, em tramitação no Senado, prevê obrigações de transparência e explicabilidade para sistemas automatizados de tomada de decisão com impacto significativo. Decisões de crédito se enquadram diretamente nessa categoria. Founders que constroem modelos de scoring com IA já devem projetar suas arquiteturas considerando a obrigação futura de justificar decisões algorítmicas.</p>\n\n<h2>Impacto prático</h2>\n<p>Para startups de IA que atuam em mercados financeiros, o caso Robbin funciona como referência de tese de investimento validada. Captações acima de US$ 100 milhões em estágio de crescimento indicam que investidores estão confortáveis com o risco regulatório do setor, desde que a startup demonstre compliance estruturado e modelo de receita recorrente comprovado.</p>\n<p>Do ponto de vista contábil, aportes dessa magnitude geralmente envolvem instrumentos híbridos: dívida conversível (notas conversíveis ou CRIs estruturados), equity com cláusulas de liquidação preferencial, ou combinação dos dois. Para o CFO ou contador da startup, cada estrutura tem tratamento contábil diferente sob o CPC 39 (Instrumentos Financeiros) e impacto distinto no patrimônio líquido, na DRE e nos covenants de futuras rodadas. Entender a natureza do instrumento captado é tão importante quanto o número do cheque.</p>\n<p>Para CTOs e diretores de tecnologia, a lição operacional é clara: infraestrutura regulada pode ser vantagem competitiva. A Robbin transformou o Pix, que é uma infraestrutura pública, em ativo proprietário de dados. Startups que constroem sobre infraestruturas abertas (Open Finance, Drex, Pix) e conseguem transformar o fluxo de dados em modelo preditivo auditável terão tese de investimento mais sólida do que aquelas que dependem de dados proprietários difíceis de escalar.</p>\n\n<h2>Considerações finais</h2>\n<p>O aporte de US$ 108 milhões na Robbin não é apenas uma notícia de rodada de investimento. É um marcador de maturidade para o segmento de fintechs com IA no Brasil. Mostra que modelos construídos sobre infraestrutura regulada, com dados transacionais reais e decisão automatizada de crédito, conseguem atrair capital institucional expressivo mesmo em um ambiente de juros ainda elevados.</p>\n<p>Para founders, advogados e contadores que trabalham com startups de IA, o recado prático é direto: estrutura jurídica e compliance regulatório não são custos acessórios, são parte do produto. Startups que constroem governança desde o início têm valuation mais defensável, captações mais rápidas e menos ruído em due diligence. O caso Robbin é evidência concreta disso.</p>",
  "faq_html": "<div class=\"faq-item\" itemscope itemtype=\"https://schema.org/Question\">\n  <p class=\"faq-pergunta\" itemprop=\"name\">Uma startup de IA pode usar dados do Pix para análise de crédito sem ser banco?</p>\n  <div class=\"faq-resposta\" itemscope itemtype=\"https://schema.org/Answer\"><span itemprop=\"text\">Sim, mas com restrições. A startup precisa estar autorizada pelo Banco Central como Fintech de Crédito (SCD ou SEP), nos termos da Resolução CMN nº 4.656/2018, ou operar em parceria formal com uma Instituição Financeira autorizada. O uso direto de dados transacionais do Pix ainda depende de autorização específica e acordo com a IF que processa as transações.</span></div>\n</div>\n<div class=\"faq-item\" itemscope itemtype=\"https://schema.org/Question\">\n  <p class=\"faq-pergunta\" itemprop=\"name\">O uso de IA para decisão de crédito exige alguma regulação específica no Brasil?</p>\n  <div class=\"faq-resposta\" itemscope itemtype=\"https://schema.org/Answer\"><span itemprop=\"text\">Hoje, a regulação direta é indireta: vem da LGPD (transparência no tratamento de dados), das normas do Banco Central sobre concessão de crédito e do Código de Defesa do Consumidor. O PL 2.338/2023, em tramitação, deve criar obrigações explícitas de explicabilidade para sistemas de IA em decisões de alto impacto, incluindo crédito. Startups devem projetar seus modelos já considerando essa exigência futura.</span></div>\n</div>\n<div class=\"faq-item\" itemscope itemtype=\"https://schema.org/Question\">\n  <p class=\"faq-pergunta\" itemprop=\"name\">Como o aporte de US$ 108 milhões é contabilizado na startup que recebe?</p>\n  <div class=\"faq-resposta\" itemscope itemtype=\"https://schema.org/Answer\"><span itemprop=\"text\">Depende do instrumento. Se for equity puro, entra como aumento de capital social ou ágio em subscrição de ações (CPC 08 e CPC 39). Se for dívida conversível, é registrado como passivo financeiro até a conversão. Instrumentos híbridos exigem análise caso a caso para separar o componente de passivo do componente de patrimônio líquido, conforme CPC 39. O tratamento contábil afeta diretamente os índices financeiros e futuros covenants.</span></div>\n</div>\n<div class=\"faq-item\" itemscope itemtype=\"https://schema.org/Question\">\n  <p class=\"faq-pergunta\" itemprop=\"name\">Qual é a diferença entre SCD e SEP para uma fintech de crédito B2B?</p>\n  <div class=\"faq-resposta\" itemscope itemtype=\"https://schema.org/Answer\"><span itemprop=\"text\">A Sociedade de Crédito Direto (SCD) empresta recursos próprios, sem captar depósitos do público. É o modelo mais comum para fintechs que usam capital de investidores para originar crédito. A Sociedade de Empréstimo entre Pessoas (SEP) faz intermediação entre credores e tomadores, funcionando como marketplace. Para crédito B2B com capital de fundo, a SCD tende a ser o veículo mais adequado.</span></div>\n</div>\n<div class=\"faq-item\" itemscope itemtype=\"https://schema.org/Question\">\n  <p class=\"faq-pergunta\" itemprop=\"name\">Startups de IA fora do setor financeiro podem aprender algo com o modelo Robbin?</p>\n  <div class=\"faq-resposta\" itemscope itemtype=\"https://schema.org/Answer\"><span itemprop=\"text\">Sim. O princípio é replicável: identificar uma infraestrutura regulada ou pública (como Open Finance, Drex ou dados de nota fiscal eletrônica), construir um modelo de IA sobre o fluxo de dados gerado por essa infraestrutura e transformar isso em serviço B2B com receita recorrente. Esse tipo de tese tem apelo claro para investidores porque combina escala com barreiras regulatórias de entrada.</span></div>\n</div>\n",
  "referencias_html": "<ul>\n<li><a href=\"https://startupi.com.br/robbin-capta-us-108-milhoes/\" target=\"_blank\" rel=\"noopener\">Startupi</a></li>\n<li>Fonte original: Startupi (https://startupi.com.br/robbin-capta-us-108-milhoes/)</li>\n<li>Banco Central do Brasil, Resolução BCB nº 1/2020 (regulamentação do Pix): https://www.bcb.gov.br</li>\n<li>Conselho Monetário Nacional, Resolução CMN nº 4.656/2018 (Fintechs de Crédito SCD e SEP): https://www.bcb.gov.br</li>\n<li>Lei nº 13.709/2018 (Lei Geral de Proteção de Dados, LGPD): https://www.planalto.gov.br/ccivil_03/_ato2015-2018/2018/lei/l13709.htm</li>\n<li>Projeto de Lei nº 2.338/2023 (Marco Legal da IA no Brasil, em tramitação no Senado): https://www25.senado.leg.br</li>\n<li>Comitê de Pronunciamentos Contábeis, CPC 39 (Instrumentos Financeiros): https://www.cpc.org.br</li>\n</ul>\n",
  "relacionados_html": "<p style=\"color:var(--cinza);font-size:0.9rem;\">Mais artigos em breve.</p>",
  "schema_json": "[\n  {\n    \"@context\": \"https://schema.org\",\n    \"@type\": \"BlogPosting\",\n    \"headline\": \"Robbin capta US$ 108 mi: IA e crédito B2B via Pix\",\n    \"description\": \"Robbin levanta US$ 108 milhões para crédito B2B com Pix. Veja o que isso significa juridicamente para fintechs e startups de IA no Brasil.\",\n    \"datePublished\": \"2026-05-22T11:01:45Z\",\n    \"dateModified\": \"2026-05-22T11:01:45Z\",\n    \"author\": {\n      \"@type\": \"Organization\",\n      \"name\": \"SAFIE\",\n      \"url\": \"https://safie.com.br\"\n    },\n    \"publisher\": {\n      \"@type\": \"Organization\",\n      \"name\": \"SAFIE IA for Business\",\n      \"url\": \"https://ia.safie.blog.br\"\n    },\n    \"url\": \"https://ia.safie.blog.br/artigos/2026-05-22-robbin-capta-us-108-mi-ia-e-credito-b2b-via-pix.html\",\n    \"articleSection\": \"Investimento em IA e deep tech\",\n    \"inLanguage\": \"pt-BR\"\n  },\n  {\n    \"@context\": \"https://schema.org\",\n    \"@type\": \"FAQPage\",\n    \"mainEntity\": [\n      {\n        \"@type\": \"Question\",\n        \"name\": \"Uma startup de IA pode usar dados do Pix para análise de crédito sem ser banco?\",\n        \"acceptedAnswer\": {\n          \"@type\": \"Answer\",\n          \"text\": \"Sim, mas com restrições. A startup precisa estar autorizada pelo Banco Central como Fintech de Crédito (SCD ou SEP), nos termos da Resolução CMN nº 4.656/2018, ou operar em parceria formal com uma Instituição Financeira autorizada. O uso direto de dados transacionais do Pix ainda depende de autorização específica e acordo com a IF que processa as transações.\"\n        }\n      },\n      {\n        \"@type\": \"Question\",\n        \"name\": \"O uso de IA para decisão de crédito exige alguma regulação específica no Brasil?\",\n        \"acceptedAnswer\": {\n          \"@type\": \"Answer\",\n          \"text\": \"Hoje, a regulação direta é indireta: vem da LGPD (transparência no tratamento de dados), das normas do Banco Central sobre concessão de crédito e do Código de Defesa do Consumidor. O PL 2.338/2023, em tramitação, deve criar obrigações explícitas de explicabilidade para sistemas de IA em decisões de alto impacto, incluindo crédito. Startups devem projetar seus modelos já considerando essa exigência futura.\"\n        }\n      },\n      {\n        \"@type\": \"Question\",\n        \"name\": \"Como o aporte de US$ 108 milhões é contabilizado na startup que recebe?\",\n        \"acceptedAnswer\": {\n          \"@type\": \"Answer\",\n          \"text\": \"Depende do instrumento. Se for equity puro, entra como aumento de capital social ou ágio em subscrição de ações (CPC 08 e CPC 39). Se for dívida conversível, é registrado como passivo financeiro até a conversão. Instrumentos híbridos exigem análise caso a caso para separar o componente de passivo do componente de patrimônio líquido, conforme CPC 39. O tratamento contábil afeta diretamente os índices financeiros e futuros covenants.\"\n        }\n      },\n      {\n        \"@type\": \"Question\",\n        \"name\": \"Qual é a diferença entre SCD e SEP para uma fintech de crédito B2B?\",\n        \"acceptedAnswer\": {\n          \"@type\": \"Answer\",\n          \"text\": \"A Sociedade de Crédito Direto (SCD) empresta recursos próprios, sem captar depósitos do público. É o modelo mais comum para fintechs que usam capital de investidores para originar crédito. A Sociedade de Empréstimo entre Pessoas (SEP) faz intermediação entre credores e tomadores, funcionando como marketplace. Para crédito B2B com capital de fundo, a SCD tende a ser o veículo mais adequado.\"\n        }\n      },\n      {\n        \"@type\": \"Question\",\n        \"name\": \"Startups de IA fora do setor financeiro podem aprender algo com o modelo Robbin?\",\n        \"acceptedAnswer\": {\n          \"@type\": \"Answer\",\n          \"text\": \"Sim. O princípio é replicável: identificar uma infraestrutura regulada ou pública (como Open Finance, Drex ou dados de nota fiscal eletrônica), construir um modelo de IA sobre o fluxo de dados gerado por essa infraestrutura e transformar isso em serviço B2B com receita recorrente. Esse tipo de tese tem apelo claro para investidores porque combina escala com barreiras regulatórias de entrada.\"\n        }\n      }\n    ]\n  }\n]",
  "palavras_corpo": 748,
  "noticia_origem": {
    "titulo": "Robbin capta US$ 108 milhões para ampliar crédito B2B com infraestrutura baseada em Pix",
    "url": "https://startupi.com.br/robbin-capta-us-108-milhoes/",
    "fonte": "Startupi",
    "data": "2026-05-22T12:00:00+00:00",
    "resumo": "<p><a href=\"https://startupi.com.br\" rel=\"nofollow\">Startupi</a><br />\n<img src=\"https://startupi.com.br/wp-content/uploads/2026/05/robbin-recebe-aporte.jpg\" style=\"display: block; margin: 1em auto;\" /><br />\n<a href=\"https://startupi.com.br/robbin-capta-us-108-milhoes/\" rel=\"nofollow\">Robbin capta ",
    "tema_slug": "investimento-ia",
    "tema_nome": "Investimento em IA e deep tech",
    "origem": "rss"
  },
  "palavras_chave": "robbin, capta, investimento, deep, tech"
}